gifgen/__init__.py
gifgen/converter.py
gifgen-1.3.0.dist-info/METADATA
gifgen-1.3.0.dist-info/WHEEL
gifgen-1.3.0.dist-info/entry_points.txt
gifgen-1.3.0.dist-info/top_level.txt
gifgen-1.3.0.dist-info/RECORD
