Metadata-Version: 2.1
Name: gifgen
Version: 1.3.0
Summary: A package to convert images in folders to GIFs
Home-page: https://github.com/rusty3699/gifgen
Author: Anish Tipnis
Author-email: rusty3699@gmail.com
Classifier: Programming Language :: Python :: 3
Classifier: Operating System :: OS Independent
Requires-Python: >=3.6
Requires-Dist: Pillow
